cursh/__init__.py
cursh/__main__.py
cursh/cli.py
cursh-1.0.5.dist-info/licenses/LICENSE
cursh-1.0.5.dist-info/METADATA
cursh-1.0.5.dist-info/WHEEL
cursh-1.0.5.dist-info/entry_points.txt
cursh-1.0.5.dist-info/top_level.txt
cursh-1.0.5.dist-info/RECORD
