Metadata-Version: 2.4
Name: cursh
Version: 1.0.5
Summary: Protect your Linux PC from viruses using a safer alternative to `curl ... | sh` or `wget ... | sh`
Author-email: Tanjim Kamal <tanjimkamal1@gmail.com>
License-Expression: MIT
Project-URL: Homepage, https://github.com/itzmetanjim/cursh
Project-URL: Issues, https://github.com/itzmetanjim/cursh/issues
Classifier: Programming Language :: Python :: 3
Classifier: Operating System :: Unix
Classifier: Development Status :: 4 - Beta
Classifier: Topic :: Security
Requires-Python: >=3.9
License-File: LICENSE
Requires-Dist: requests
Requires-Dist: colorama
Dynamic: license-file
